{
  "companyName" : "I Scream Inc.",
  "headOffice" : "South Pole, Antarctica",
  "established" : 2001,
  "active" : true,
  "topFlavors" : [
    {
      "name" : "Monstrous Mint",
      "calories" : 400,
      "type" : "ice cream",
      "ingredients" : [
        "peppermint cream",
        "dark chocolate chips",
        "vanilla extract"
      ],
      "image" : "chocolate-mint.svg"
    },
    {
      "name" : "Perfect Peach Mango",
      "calories" : 350,
      "type" : "sorbet",
      "ingredients" : [
        "peach puree",
        "mango chunks",
        "clover honey"
      ],
      "image" : "peach-mango.svg"
    },
    {
      "name" : "Strawberry Swirl Dream",
      "calories" : 300,
      "type" : "ice cream",
      "ingredients" : [
        "Fresh strawberries",
        "Vanilla",
        "Whole milk"
      ],
      "image" : "ice-cream-xtra1.svg"
    },
    {
      "name" : "Chocolate Fudge Delight",
      "calories" : 250,
      "type" : "ice cream",
      "ingredients" : [
        "Cocoa powder",
        "Heavy cream",
        "Chocolate chips"
      ],
      "image" : "ice-cream-xtra2.svg"
    }
  ]
}